requirements.txt
setup.cfg
setup.py
wrang_utils/__init__.py
wrang_utils/aws_utils.py
wrang_utils/dynamo_utils.py
wrang_utils/graphql_utils.py
wrang_utils/handler.py
wrang_utils/model_utils.py
wrang_utils/python_utils.py
wrang_utils/version.py
wrang_utils.egg-info/PKG-INFO
wrang_utils.egg-info/SOURCES.txt
wrang_utils.egg-info/dependency_links.txt
wrang_utils.egg-info/requires.txt
wrang_utils.egg-info/top_level.txt
wrang_utils/graphql_to_python/__init__.py
wrang_utils/graphql_to_python/query.py
wrang_utils/models/__init__.py
wrang_utils/models/graphql.py