Metadata-Version: 2.1
Name: wrang-utils
Version: 1.0.1
Summary: Wrangled Insights utilities
Home-page: UNKNOWN
Author: Conrad Moss
Author-email: cmoss@wrangledinsights.com
License: UNKNOWN
Platform: UNKNOWN
Provides-Extra: dev
